pyhtelasso/__init__.py
pyhtelasso/pyhtelasso.py
pyhtelasso-0.2.0.dist-info/licenses/LICENSE
pyhtelasso-0.2.0.dist-info/METADATA
pyhtelasso-0.2.0.dist-info/WHEEL
pyhtelasso-0.2.0.dist-info/top_level.txt
pyhtelasso-0.2.0.dist-info/RECORD
