Metadata-Version: 2.4
Name: pyhtelasso
Version: 0.2.0
Summary: A Python package for detecting treatment effect heterogeneity using debiased lasso
Home-page: https://github.com/vyasenov/pyhtelasso
Author: Vasco Yasenov
Author-email: yasenov@gmail.com
Project-URL: Bug Reports, https://github.com/vyasenov/pyhtelasso/issues
Project-URL: Source, https://github.com/vyasenov/pyhtelasso
Project-URL: Documentation, https://github.com/vyasenov/pyhtelasso#readme
Keywords: causal inference,treatment effects,heterogeneity,lasso,debiased lasso,econometrics
Classifier: Development Status :: 3 - Alpha
Classifier: Intended Audience :: Science/Research
Classifier: License :: OSI Approved :: MIT License
Classifier: Operating System :: OS Independent
Classifier: Programming Language :: Python :: 3
Classifier: Programming Language :: Python :: 3.7
Classifier: Programming Language :: Python :: 3.8
Classifier: Programming Language :: Python :: 3.9
Classifier: Programming Language :: Python :: 3.10
Classifier: Programming Language :: Python :: 3.11
Classifier: Topic :: Scientific/Engineering :: Information Analysis
Classifier: Topic :: Scientific/Engineering :: Mathematics
Requires-Python: >=3.7
License-File: LICENSE
Requires-Dist: numpy>=1.19.0
Requires-Dist: scikit-learn>=1.0.0
Requires-Dist: pandas>=1.3.0
Requires-Dist: scipy>=1.7.0
Requires-Dist: econml>=0.13.0
Provides-Extra: dev
Requires-Dist: pytest>=6.0; extra == "dev"
Requires-Dist: pytest-cov>=2.0; extra == "dev"
Requires-Dist: black>=21.0; extra == "dev"
Requires-Dist: flake8>=3.8; extra == "dev"
Requires-Dist: mypy>=0.800; extra == "dev"
Provides-Extra: full
Requires-Dist: econml>=0.13.0; extra == "full"
Requires-Dist: scipy>=1.7.0; extra == "full"
Dynamic: author
Dynamic: author-email
Dynamic: classifier
Dynamic: description
Dynamic: description-content-type
Dynamic: home-page
Dynamic: keywords
Dynamic: license-file
Dynamic: project-url
Dynamic: provides-extra
Dynamic: requires-dist
Dynamic: requires-python
Dynamic: summary
